augment_layers/__init__.py
augment_layers/background.py
augment_layers/color_cast.py
augment_layers/color_temperature.py
augment_layers/rgba.py
tf_image_augment_layers-0.1.1.dist-info/licenses/LICENSE
tf_image_augment_layers-0.1.1.dist-info/METADATA
tf_image_augment_layers-0.1.1.dist-info/WHEEL
tf_image_augment_layers-0.1.1.dist-info/top_level.txt
tf_image_augment_layers-0.1.1.dist-info/RECORD
