Metadata-Version: 2.4
Name: tf-image-augment-layers
Version: 0.1.1
Summary: TensorFlow augmentation layers including RGBA background compositing, random color temperature, and color cast.
Author-email: Nao <ozawa_naomitsu@kurume-u.ac.jp>
License: MIT License
Project-URL: Homepage, https://https://github.com/naomitsu-ozawa/WB_augmentor_for_tensorflow
Project-URL: Source, https://github.com/naomitsu-ozawa/WB_augmentor_for_tensorflow
Keywords: tensorflow,augmentation,image-processing,keras
Requires-Python: >=3.8
License-File: LICENSE
Requires-Dist: tensorflow<=2.15.1,>=2.13.2
Dynamic: license-file
